{
  "name": "ImageMaskProcessor",
  "description": "2D image thresholding and region analysis",
  "container-image": {
    "image": "alexandrumihai2020/w-imagemaskprocessor",
    "type": "singularity"
  },
  "command-line": "python wrapper.py --min-thresh @min_thresh --min-area @min_area",
  "inputs": [
    {
      "id": "min_thresh",
      "value-key": "@min_thresh",
      "command-line-flag": "--min-thresh",
      "name": "Minimum threshold",
      "description": "Minimum intensity threshold (0-255). Pixels with value >= threshold are kept as foreground.",
      "default-value": 10,
      "set-by-server": false,
      "optional": true,
      "type": "Number"
    },
    {
      "id": "min_area",
      "value-key": "@min_area",
      "command-line-flag": "--min-area",
      "name": "Minimum area",
      "description": "Minimum area in pixels for region filtering. Regions smaller than this will be excluded.",
      "default-value": 1.0,
      "set-by-server": false,
      "optional": true,
      "type": "Number"
    }
  ],

  "schema-version": "cytomine-0.1"
}
